{
    "homepage": "https://brave.com",
    "version": "1.50.56",
    "description": "Secure, Fast & Private Web Browser with Adblocker (nightly release)",
    "license": {
        "identifier": "Freeware,BSD-3-Clause,GPL-3.0-only,...",
        "url": "https://github.com/brave/brave-browser/blob/master/LICENSE"
    },
    "architecture": {
        "64bit": {
            "url": "https://github.com/brave/brave-browser/releases/download/v1.50.56/brave-v1.50.56-win32-x64.zip",
            "hash": "eaa3acfa2002fcea54aa0af3fd4eca86f910675b3ae18b78f69b20360fd874f8"
        }
    },
    "bin": [
        [
            "brave.exe",
            "brave-nightly"
        ]
    ],
    "shortcuts": [
        [
            "brave.exe",
            "Brave Nightly"
        ]
    ],
    "checkver": {
        "url": "https://github.com/brave/brave-browser/releases",
        "regex": "Nightly v([\\d.]+)"
    },
    "autoupdate": {
        "architecture": {
            "64bit": {
                "url": "https://github.com/brave/brave-browser/releases/download/v$version/brave-v$version-win32-x64.zip"
            }
        }
    }
}
