{
    "homepage": "https://brave.com",
    "version": "1.39.31",
    "description": "Secure, Fast & Private Web Browser with Adblocker (nightly release)",
    "license": {
        "identifier": "Freeware,BSD-3-Clause,GPL-3.0-only,...",
        "url": "https://github.com/brave/brave-browser/blob/master/LICENSE"
    },
    "architecture": {
        "64bit": {
            "url": "https://github.com/brave/brave-browser/releases/download/v1.39.31/brave-v1.39.31-win32-x64.zip",
            "hash": "1740a4a0fc5a2f2e28f22063f08bac6be8b5d9c6815cb4a93be06914a41ae2e7"
        }
    },
    "bin": [
        [
            "brave.exe",
            "brave-nightly"
        ]
    ],
    "shortcuts": [
        [
            "brave.exe",
            "Brave Nightly"
        ]
    ],
    "checkver": {
        "url": "https://github.com/brave/brave-browser/releases",
        "regex": "Nightly v([\\d.]+)"
    },
    "autoupdate": {
        "architecture": {
            "64bit": {
                "url": "https://github.com/brave/brave-browser/releases/download/v$version/brave-v$version-win32-x64.zip"
            }
        }
    }
}
