{
    "homepage": "https://brave.com",
    "version": "1.65.25",
    "description": "Secure, Fast & Private Web Browser with Adblocker (nightly release)",
    "license": {
        "identifier": "Freeware,BSD-3-Clause,GPL-3.0-only,...",
        "url": "https://github.com/brave/brave-browser/blob/master/LICENSE"
    },
    "architecture": {
        "64bit": {
            "url": "https://github.com/brave/brave-browser/releases/download/v1.65.25/brave-v1.65.25-win32-x64.zip",
            "hash": "d824c1a4a2608c977f464e9fb60fa9c015933f9302834ff41d3470279d1e62d9"
        }
    },
    "bin": [
        [
            "brave.exe",
            "brave-nightly"
        ]
    ],
    "shortcuts": [
        [
            "brave.exe",
            "Brave Nightly"
        ]
    ],
    "checkver": {
        "url": "https://github.com/brave/brave-browser/releases",
        "regex": "Nightly v([\\d.]+)"
    },
    "autoupdate": {
        "architecture": {
            "64bit": {
                "url": "https://github.com/brave/brave-browser/releases/download/v$version/brave-v$version-win32-x64.zip"
            }
        }
    }
}
