{
    "version": "104.0a1.20220704214252",
    "description": "Nightly builds of Firefox: the popular open source web browser.",
    "homepage": "https://www.mozilla.org/en-US/firefox/nightly/",
    "license": "MPL-2.0",
    "notes": [
        "To set profile 'Scoop-Nightly' as *DEFAULT*, or profiles/settings was lost after update:",
        "  - Run 'Firefox Nightly Profile Manager', choose 'Scoop-Nightly' then click 'Start Nightly'.",
        "  - Visit 'about:profiles' page in Firefox Nightly to check *DEFAULT* profile.",
        "For details: https://support.mozilla.org/en-US/kb/profile-manager-create-remove-switch-firefox-profiles"
    ],
    "architecture": {
        "64bit": {
            "url": "https://archive.mozilla.org/pub/firefox/nightly/2022/07/2022-07-04-21-42-52-mozilla-central/firefox-104.0a1.en-US.win64.installer.exe#/dl.7z",
            "hash": "sha512:6d0247d1493e8aad9560865a31bb04a9d03e835858558e6c3717f7c8b5c2c4f3a53e61fa94131f749f4cd8fe8572996d795986a753bbef5716a87a92cb7ab3f1"
        },
        "32bit": {
            "url": "https://archive.mozilla.org/pub/firefox/nightly/2022/07/2022-07-04-21-42-52-mozilla-central/firefox-104.0a1.en-US.win32.installer.exe#/dl.7z",
            "hash": "sha512:347bd6d2a9dac455f7443b6cb8f9f66205c9b8bbd045149b9a7d93083cde4821bab480696ba4556e7f64c244ab137f701f7151a0efed2c605be680247aecec85"
        }
    },
    "extract_dir": "core",
    "post_install": [
        "firefox-nightly -CreateProfile \"Scoop-Nightly $persist_dir\\profile\"",
        "$Addition = \"$persist_dir\\addition\"",
        "if (Test-Path $Addition) {",
        "  info 'Copying additional items...'",
        "  Copy-Item -Path $Addition\\* -Destination $dir -Force -Recurse -ErrorAction SilentlyContinue",
        "}"
    ],
    "bin": [
        [
            "firefox.exe",
            "firefox-nightly"
        ]
    ],
    "shortcuts": [
        [
            "firefox.exe",
            "Firefox Nightly"
        ],
        [
            "firefox.exe",
            "Firefox Nightly Profile Manager",
            "-P"
        ]
    ],
    "persist": [
        "distribution",
        "profile"
    ],
    "checkver": {
        "url": "https://aus5.mozilla.org/update/6/Firefox/60.0/_/WINNT_x86_64-msvc-x64/en-US/nightly/_/_/_/_/update.xml",
        "regex": "appVersion=\"([\\w.]+)\".*?buildID=\"((?<yyyy>\\d{4})(?<mm>\\d{2})(?<dd>\\d{2})(?<hr>\\d{2})(?<mi>\\d{2})(?<se>\\d{2}))",
        "replace": "${1}.${2}"
    },
    "autoupdate": {
        "architecture": {
            "64bit": {
                "url": "https://archive.mozilla.org/pub/firefox/nightly/$matchYyyy/$matchMm/$matchYyyy-$matchMm-$matchDd-$matchHr-$matchMi-$matchSe-mozilla-central/firefox-$majorVersion.$minorVersion.en-US.win64.installer.exe#/dl.7z",
                "hash": {
                    "url": "$baseurl/firefox-$majorVersion.$minorVersion.en-US.win64.checksums"
                }
            },
            "32bit": {
                "url": "https://archive.mozilla.org/pub/firefox/nightly/$matchYyyy/$matchMm/$matchYyyy-$matchMm-$matchDd-$matchHr-$matchMi-$matchSe-mozilla-central/firefox-$majorVersion.$minorVersion.en-US.win32.installer.exe#/dl.7z",
                "hash": {
                    "url": "$baseurl/firefox-$majorVersion.$minorVersion.en-US.win32.checksums"
                }
            }
        }
    }
}
