{
    "homepage": "https://rclone.org",
    "description": "rsync for cloud storage",
    "version": "1.46.0-095-g1bd8183a",
    "license": "MIT",
    "architecture": {
        "64bit": {
            "url": "https://beta.rclone.org/v1.46.0-095-g1bd8183a-beta/rclone-v1.46.0-095-g1bd8183a-beta-windows-amd64.zip",
            "extract_dir": "rclone-v1.46.0-095-g1bd8183a-beta-windows-amd64",
            "hash": "52e1f925b0dde1065ad6e41c4c5d49bc483fd752fa04789e450490e1e58ebc3b"
        },
        "32bit": {
            "url": "https://beta.rclone.org/v1.46.0-095-g1bd8183a-beta/rclone-v1.46.0-095-g1bd8183a-beta-windows-386.zip",
            "extract_dir": "rclone-v1.46.0-095-g1bd8183a-beta-windows-386",
            "hash": "3fb9ff2b71cc20f62e60bce2fd464a6b4cfe5c9a9492714752b6777cfbd278df"
        }
    },
    "bin": [
        "rclone.exe",
        [
            "rclone.exe",
            "rclone-beta"
        ]
    ],
    "checkver": {
        "url": "https://beta.rclone.org/version.txt",
        "regex": "rclone v(.+)-beta"
    },
    "autoupdate": {
        "architecture": {
            "64bit": {
                "url": "https://beta.rclone.org/v$version-beta/rclone-v$version-beta-windows-amd64.zip",
                "extract_dir": "rclone-v$version-beta-windows-amd64"
            },
            "32bit": {
                "url": "https://beta.rclone.org/v$version-beta/rclone-v$version-beta-windows-386.zip",
                "extract_dir": "rclone-v$version-beta-windows-386"
            }
        }
    }
}
