{
    "homepage": "http://www.7-zip.org/",
    "description": "Multi-format compression/decompression tool (beta version)",
    "license": "LGPL-2.1",
    "version": "18.02",
    "architecture": {
        "64bit": {
            "url": "http://7-zip.org/a/7z1802-x64.msi",
            "hash": "65d1aa4de97d3a44480471629f1c1bf7effa7199a75b68cc9c6c2279fab2945f"
        },
        "32bit": {
            "url": "http://7-zip.org/a/7z1802.msi",
            "hash": "48056bf04e930915b465bfdd1be6adb4421e9786ff82628ec2cb1fe1b0da80c8"
        }
    },
    "extract_dir": "Files/7-Zip",
    "bin": [
        "7z.exe",
        "7zG.exe"
    ],
    "checkver": {
        "re": "Download 7-Zip ([\\d.]+) beta",
        "url": "http://www.7-zip.org/download.html"
    },
    "autoupdate": {
        "architecture": {
            "64bit": {
                "url": "http://7-zip.org/a/7z$cleanVersion-x64.msi"
            },
            "32bit": {
                "url": "http://7-zip.org/a/7z$cleanVersion.msi"
            }
        }
    },
    "shortcuts": [
        [
            "7zFM.exe",
            "7zip"
        ]
    ]
}
